kf6py/__init__.py
kf6py/api.py
kf6py-0.2.4.dist-info/METADATA
kf6py-0.2.4.dist-info/WHEEL
kf6py-0.2.4.dist-info/licenses/LICENSE
kf6py-0.2.4.dist-info/RECORD
