Metadata-Version: 2.1
Name: kf6py
Version: 0.2.4
Summary: A small tool for calling APIs in Knowledge Forum
Project-URL: Homepage, https://github.com/JerrisonChang/kf6api-py
Project-URL: Bug Tracker, https://github.com/JerrisonChang/kf6api-py/issues
Author-email: Jerrison Chang-Sundin <chunyen.cs@gmail.com>
License-File: LICENSE
Classifier: License :: OSI Approved :: MIT License
Classifier: Operating System :: OS Independent
Classifier: Programming Language :: Python :: 3
Requires-Python: >=3.7
Requires-Dist: beautifulsoup4<5,>=4
Requires-Dist: requests<3,>=2.28
